src/__init__.py
src/vibeAI24.py
vibeAI24-1.0.3.dist-info/LICENSE
vibeAI24-1.0.3.dist-info/METADATA
vibeAI24-1.0.3.dist-info/WHEEL
vibeAI24-1.0.3.dist-info/top_level.txt
vibeAI24-1.0.3.dist-info/RECORD
