Metadata-Version: 2.1
Name: vibeAI24
Version: 1.0.3
Summary: A library for predicting and blocking suspicious traffic
Home-page: UNKNOWN
Author: Vibe AI
Author-email: contactvibe615@gmail.com
License: UNKNOWN
Keywords: cyberAI,AIcyber,vibeAI24
Platform: UNKNOWN
Classifier: Programming Language :: Python :: 3
Classifier: License :: OSI Approved :: MIT License
Classifier: Operating System :: OS Independent
Requires-Python: >=3.6
Requires-Dist: numpy
Requires-Dist: pandas
Requires-Dist: pydantic
